attune/VERSION
attune/__init__.py
attune/__version__.py
attune/_arrangement.py
attune/_cli.py
attune/_common.py
attune/_discrete_tune.py
attune/_holistic.py
attune/_instrument.py
attune/_intensity.py
attune/_map.py
attune/_note.py
attune/_offset.py
attune/_open.py
attune/_plot.py
attune/_rename.py
attune/_setable.py
attune/_setpoint.py
attune/_store.py
attune/_transition.py
attune/_tune.py
attune/_tune_test.py
attune/_update_merge.py
attune/io/__init__.py
attune/io/topas3.py
attune/io/topas4.py
attune-0.5.1.dist-info/LICENSE
attune-0.5.1.dist-info/METADATA
attune-0.5.1.dist-info/WHEEL
attune-0.5.1.dist-info/entry_points.txt
attune-0.5.1.dist-info/top_level.txt
attune-0.5.1.dist-info/RECORD
